nhkv/CompactStorage.py
nhkv/DbDict.py
nhkv/DbOffsetStorage.py
nhkv/KVStore.py
nhkv/__init__.py
nhkv-0.0.1.dist-info/LICENCE
nhkv-0.0.1.dist-info/METADATA
nhkv-0.0.1.dist-info/WHEEL
nhkv-0.0.1.dist-info/top_level.txt
nhkv-0.0.1.dist-info/RECORD
