Metadata-Version: 2.1
Name: nhkv
Version: 0.0.1
Summary: Library for simple key-value storage
Author: Vitaly R
Project-URL: Homepage, https://github.com/VitalyRomanov/nhkv
Project-URL: Bug Tracker, https://github.com/VitalyRomanov/nhkv/issues
Classifier: Programming Language :: Python :: 3
Classifier: License :: OSI Approved :: MIT License
Classifier: Operating System :: OS Independent
Requires-Python: >=3.7
License-File: LICENCE
Requires-Dist: dill
